{
  "tables": [
    {
      "id": "1",
      "numero": 1,
      "estado": "libre"
    },
    {
      "id": "2",
      "numero": 2,
      "estado": "libre"
    },
    {
      "id": "3",
      "numero": 3,
      "estado": "libre"
    },
    {
      "id": "4",
      "numero": 4,
      "estado": "libre"
    },
    {
      "id": "5",
      "numero": 5,
      "estado": "libre"
    },
    {
      "id": "6",
      "numero": 6,
      "estado": "libre"
    },
    {
      "id": "7",
      "numero": 7,
      "estado": "libre"
    },
    {
      "id": "8",
      "numero": 8,
      "estado": "libre"
    },
    {
      "id": "9",
      "numero": 9,
      "estado": "libre"
    },
    {
      "id": "10",
      "numero": 10,
      "estado": "libre"
    },
    {
      "id": "11",
      "numero": 11,
      "estado": "libre"
    },
    {
      "id": "12",
      "numero": 12,
      "estado": "libre"
    }
  ],
  "orders": [],
  "history": [
    {
      "id": "Z-20260401-858",
      "mesa_numero": 0,
      "hora": "11:11:03",
      "fecha_ISO": "2026-04-01",
      "items": [
        {
          "id": "z1",
          "nombre": "REPORTE Z ACUMULADO",
          "descripcion": "Ventas del día",
          "precio_COP": 204520,
          "categoria": "ADMIN",
          "cantidad": 1,
          "status": "ready",
          "tableId": "0",
          "lineId": "z1"
        }
      ],
      "subtotal_COP": 184000,
      "tax_COP": 14720,
      "tip_COP": 5800,
      "tip_percentage": 0,
      "total_COP": 204520,
      "estado": "PAGADO"
    },
    {
      "id": "F-1414",
      "mesa_numero": 3,
      "hora": "10:48",
      "fecha_ISO": "2026-04-01",
      "items": [
        {
          "id": "m1",
          "nombre": "Carpaccio de Res",
          "descripcion": "Láminas finas de solomillo, alcaparras, parmesano y aceite de trufa.",
          "precio_COP": 42000,
          "categoria": "Entradas",
          "cantidad": 5,
          "status": "sent",
          "tableId": "3",
          "lineId": "l-1775055858930-4ozth80xk",
          "comandaId": "#2031"
        },
        {
          "id": "m3",
          "nombre": "Risotto de Hongos",
          "descripcion": "Arroz arborio, variedad de setas silvestres y aceite de trufa blanca.",
          "precio_COP": 65000,
          "categoria": "Fuertes",
          "cantidad": 3,
          "status": "sent",
          "tableId": "3",
          "lineId": "l-1775055861338-k191gz9am",
          "comandaId": "#2031"
        },
        {
          "id": "m5",
          "nombre": "Malbec Reserva",
          "descripcion": "Copa de vino tinto con notas de frutos rojos y roble.",
          "precio_COP": 35000,
          "categoria": "Vinos",
          "cantidad": 1,
          "status": "sent",
          "tableId": "3",
          "lineId": "l-1775055932515-44jykk062",
          "comandaId": "#3760"
        },
        {
          "id": "m5",
          "nombre": "Malbec Reserva",
          "descripcion": "Copa de vino tinto con notas de frutos rojos y roble.",
          "precio_COP": 35000,
          "categoria": "Vinos",
          "cantidad": 3,
          "status": "sent",
          "tableId": "3",
          "lineId": "l-1775055939227-z8kvbhrsj",
          "comandaId": "#5140"
        }
      ],
      "subtotal_COP": 545000,
      "tax_COP": 43600,
      "tip_COP": 0,
      "tip_percentage": 0,
      "total_COP": 588600,
      "estado": "ANULADO"
    }
  ],
  "tips": {},
  "pendingCaja": {},
  "menuItems": [
    {
      "id": "m1",
      "nombre": "Carpaccio de Res",
      "descripcion": "Láminas finas de solomillo, alcaparras, parmesano y aceite de trufa.",
      "precio_COP": 42000,
      "categoria": "Entradas"
    },
    {
      "id": "m2",
      "nombre": "Pulpo a la Brasa",
      "descripcion": "Tentáculo de pulpo, puré de papa criolla y pimentón de la vera.",
      "precio_COP": 58000,
      "categoria": "Entradas"
    },
    {
      "id": "m3",
      "nombre": "Risotto de Hongos",
      "descripcion": "Arroz arborio, variedad de setas silvestres y aceite de trufa blanca.",
      "precio_COP": 65000,
      "categoria": "Fuertes"
    },
    {
      "id": "m4",
      "nombre": "Salmón en Costra",
      "descripcion": "Filete de salmón con costra de pistacho y espárragos trigueros.",
      "precio_COP": 72000,
      "categoria": "Fuertes"
    },
    {
      "id": "m5",
      "nombre": "Malbec Reserva",
      "descripcion": "Copa de vino tinto con notas de frutos rojos y roble.",
      "precio_COP": 35000,
      "categoria": "Vinos"
    }
  ],
  "staff": [
    {
      "id": "s1",
      "nombre": "CARLOS MENDOZA",
      "rol": "MESERO SENIOR",
      "pin": "1111"
    },
    {
      "id": "s2",
      "nombre": "ANA GARCÍA",
      "rol": "MESERA",
      "pin": "2222"
    },
    {
      "id": "s3",
      "nombre": "LUIS TORRES",
      "rol": "MESERO",
      "pin": "3333"
    }
  ],
  "lastUpdate": 1775067527888
}